{
  "id": "ma-arrete-1148-25",
  "type": "statute",
  "title": "Arrêté conjoint n° 1148/25 portant approbation de la convention instituant le Centre d’Innovation en Cybersécurité",
  "title_en": "Joint Order No. 1148/25 Approving the Convention Establishing the Cybersecurity Innovation Center",
  "short_name": "Arrêté 1148/25",
  "status": "in_force",
  "issued_date": "2025-06-01",
  "url": "https://www.dgssi.gov.ma/fr/textes-legislatifs-et-reglementaires/publication-de-larrete-conjoint-ndeg-114825-portant",
  "description": "Convention instituant le Centre d’Innovation en Cybersécurité.",
  "provisions": [],
  "definitions": [],
  "ingestion_status": "skipped",
  "ingestion_notes": "No extractable article headings found (likely image-only PDF or inaccessible source text)."
}