{
  "id": "ma-adala-electoral-8461",
  "type": "statute",
  "title": "ظهیر شريف بتمديد مدة انتداب الأعضاء المنتخبين بالغرف الفلاحية",
  "status": "in_force",
  "url": "https://adala.justice.gov.ma/resources/41",
  "description": "Discovered from Adala portal, folder: electoral (المادة الإنتخابية).",
  "provisions": [
    {
      "provision_ref": "art1",
      "section": "1",
      "title": "المادة 1",
      "content": "إن مدة انتداب األعضاء المنتخبين بالغرف الفالحية المزاولين اآلن مهامهم تمدد إلى نهاية\nانتداب مجلس النواب الذي سيشرع في أعماله خالل سنة .1970"
    },
    {
      "provision_ref": "art2",
      "section": "2",
      "title": "المادة 2",
      "content": "يسند تنفيذ ظهيرنا الشريف هذا الذي ينشر بالجريدة الرسمية إلى وزير الدولة المكلف\nبالفالحة واإلصالح الزراعي ووزير الداخلية كل واحد منهما فيما يخصه.\nوحرر بالرباط في 27جمادى األولى 31( 1390يوليوز .)1970\n\n -1الجريدة الرسمية عدد 3013مكرر بتاريخ 28جمادى األولى ( 1390فاتح غشت ،(1970ص .1952\n-2-"
    }
  ],
  "definitions": [],
  "ingestion_status": "ingested"
}