{
  "id": "ma-adala-administrative-5960",
  "type": "statute",
  "title": "مرسوم بإحداث أجرة عن الخدمات المقدمة من قبل المندوبية السامية لقدماء المقاومين وأعضاء جيش التحرير",
  "status": "in_force",
  "url": "https://adala.justice.gov.ma/resources/26",
  "description": "Discovered from Adala portal, folder: administrative (القانون الإداري).",
  "provisions": [
    {
      "provision_ref": "art1",
      "section": "1",
      "title": "المادة 1",
      "content": "ى\nتحدث أجرة عن الخدمات المقدمة من قبل المندوبية السامية القدماء المقاومين وأعضاء\nجيش التحرير فيما يخص بيع ما تصدره أو يصدر لفائدتها من منشورات وما تنتجه أو تعيد\nإنتاجه من وثائق مطبوعة أو مخطوطة أو صوتية أو مرئية أو غيرها وكذا فيما يتعلق بإنتاج\nاألشرطة السينمائية واألشرطة الوثائقية المرتبطة بفصول ملحمة االستقالل.\nيمكن تسويق اإلصدارات والمنشورات المشار إليها أعاله عن طريق العمولة المخولة\nلشركات التوزيع ولكل فاعل تجاري أو ثقافي ،وذلك بموجب عقد يبرم بين الطرفين.\nكما تخصص نسبة %20من اإلصدارات والمنشورات لإلهداء بالمجان."
    },
    {
      "provision_ref": "art2",
      "section": "2",
      "title": "المادة 2",
      "content": "ة\nتحدد تعريفات الخدمات المشار إليها في المادة األولى أعاله بقرار مشترك للوزير األول\nووزير المالية والخوصصة."
    },
    {
      "provision_ref": "art3",
      "section": "3",
      "title": "المادة 3",
      "content": "ة\nتحصل موارد الخدمات المشار إليها أعاله لفائدة الميزانية العامة."
    },
    {
      "provision_ref": "art4",
      "section": "4",
      "title": "المادة 4",
      "content": "ة\nيسند إلى المندوب السامي القدماء المقاومين وأعضاء جيش التحرير ووزير المالية\nوالخوصصة ،كل واحد منهما فيما يخصه ،تنفيذ هذا المرسوم الذي يعمل بأحكامه ابتداء من\nتاريخ نشره بالجريدة الرسمية.\nوحرر بالرباط في 29من جمادى اآلخرة 5( 1426أغسطس .)2005\nاإلمضاء :إدريس جطو.\nوقعه بالعطف:\nوزير المالية والخوصصة،\nاإلمضاء :فتح هللا ولعلو.\n\n -2تم تتميم أحكام هذه المادة بموجب المادة األولى من المرسوم رقم 2.08.284صادر في 5جمادى اآلخرة 1429\n( 9يونيو ،)2008الجريدة الرسمية عدد 5642بتاريخ 22جمادى اآلخرة 26( 1429يونيو ،)2008ص .1471\n تم نسخ أحكام الفقرة األخيرة من هذه المادة بموجب المادة األولى من المرسوم رقم 2.18.185صادر في 24منشعبان 11( 1439ماي ،)2018الجريدة الرسمية عدد 6678بتاريخ 15رمضان 31( 1439ماي ،)2018ص\n.3067\n4"
    }
  ],
  "definitions": [],
  "ingestion_status": "ingested"
}