{
  "id": "ma-adala-financial-5743",
  "type": "statute",
  "title": "مرسوم يتعلق بتحديد عدد اللجان الجهوية للنظر في الطعون المتعلقة بالضريبة ومقارها ودوائر اختصاصها",
  "status": "in_force",
  "url": "https://adala.justice.gov.ma/resources/829",
  "description": "Discovered from Adala portal, folder: financial (المادة المالية).",
  "provisions": [
    {
      "provision_ref": "art1",
      "section": "1",
      "title": "المادة 1",
      "content": "ى\nيحدد عدد اللجان الجهوية للنظر في الطعون المتعلقة بالضريبة في تسع ( )9لجان تعين\nمقارها ودوائر اختصاصها في الجدول الملحق بهذا المرسوم."
    },
    {
      "provision_ref": "art2",
      "section": "2",
      "title": "المادة 2",
      "content": "ة\nيسند إلى الوزير المنتدب لدى وزيرة االقتصاد والمالية المكلف بالميزانية ووزير العدل،\nكل فيما يخصه ،تنفيذ هذا المرسوم الذي ينشر بالجريدة الرسمية.\n\n - 1الجريدة الرسمية عدد 7136بتاريخ 23ربيع األول 20( 1444أكتوبر ،)2022ص .6624\n-2-\n\nوحرر بالرباط في 9ربيع األول 6( 1444أكتوبر .)2022\nاإلمضاء :عزيز أخنوش.\nوقعه بالعطف:\nالوزير المنتدب لدى وزيرة االقتصاد\nوالمالية المكلف بالميزانية،\nاإلمضاء :فوزي لقجع.\nوزير العدل،\nاإلمضاء :عبد اللطيف وهبي.\n\n-3-\n\nملحق بالمرسوم رقم 2.22.573الصادر في 9ربيع األول 1444\n( 6أكتوبر )2022بتحديد عدد اللجان الجهوية للنظر في الطعون المتعلقة\nبالضريبة ومقارها ودوائر اختصاصها\nمقار ودوائر اختصاص اللجان الجهوية للنظر في الطعون المتعلقة بالضريبة\nاللجان الجهوية للنظر في\nالطعون المتعلقة بالضريبة\n\nمقار اللجان الجهوية للنظر في\nالطعون المتعلقة بالضريبة\n\nاللجنة الجهوية للنظر في الطعون\nالمتعلقة بالضريبة بالدار البيضاء\n\nالمحكمة اإلدارية بالدار البيضاء\n\nاللجنة الجهوية للنظر في الطعون\nالمتعلقة بالضريبة بالرباط\n\nالمحكمة اإلدارية بالرباط\n\nاللجنة الجهوية للنظر في الطعون\nالمتعلقة بالضريبة بفاس\n\nالمحكمة اإلدارية بفاس\n\n-4-\n\nدوائر اختصاص اللجان الجهوية للنظر\nفي الطعون المتعلقة بالضريبة -عماالت\nوأقاليم\nالدار البيضاء\nالمحمدية\nالجديدة\nالنواصر\nمديونة\nبنسليمان\nبرشيد\nسطات\nسيدي بنور\nالرباط\nسال\nالصخيرات -تمارة\nالقنيطرة\nالخميسات\nسيدي قاسم\nسيدي سليمان\nفاس\nمكناس\nالحاجب\nإيفران\nموالي يعقوب\nصفرو\nبولمان\nتاونات\nتازة\n\nاللجان الجهوية للنظر في الطعون\nالمتعلقة بالضريبة\n\nمقار اللجان الجهوية للنظر في\nالطعون المتعلقة بالضريبة\n\nاللجنة الجهوية للنظر في الطعون المتعلقة\nبالضريبة بمراكش\n\nالمحكمة اإلدارية بمراكش\n\nاللجنة الجهوية للنظر في الطعون المتعلقة\nبالضريبة بأكادير\n\nالمحكمة اإلدارية بأكادير\n\nاللجنة الجهوية للنظر في الطعون المتعلقة\nبالضريبة بوجدة\n\nالمحكمة اإلدارية بوجدة\n\nاللجنة الجهوية للنظر في الطعون المتعلقة\nبالضريبة بطنجة\n\nالمحكمة االبتدائية بطنجة\n\nاللجنة الجهوية للنظر في الطعون المتعلقة\nبالضريبة ببني مالل\n\nالمحكمة االبتدائية ببني مالل\n\nاللجنة الجهوية للنظر في الطعون المتعلقة\nبالضريبة بالرشيدية\n\nالمحكمة االبتدائية بالرشيدية\n\n-5-\n\nدوائر اختصاص اللجان الجهوية\nللنظر في الطعون المتعلقة\nبالضريبة -عماالت وأقاليم\nمراكش\nشيشاوة\nالحوز\nقلعة السراغنة\nالصويرة\nالرحامنة\nآسفي\nاليوسفية\nأكادير إداوتنان\nإنزكان آيت ملول\nاشتوكة آيت باها\nتارودانت\nتيزنيت\nطاطا\nكلميم\nآسا -الزاك\nطانطان\nسيدي افني\nالعيون\nبوجدور\nطرفاية\nالسمارة\nوادي الذهب\nأو سرد\nوجدة -أنجاد\nالناضور\nالدريوش\nجرادة\nبركان\nتاوريرت\nجرسيف\nفجيج\nطنجة -أصيلة\nالمضيق -الفنيدق\nتطوان\nالفحص -أنجرة\nالعرائش\nالحسيمة\nشفشاون\nوزان\nبني مالل\nأزيالل\nالفقيه بن صالح\nخنيفرة\nخريبكة\nالرشيدية\nورزازات\nميدلت\nتنغير\nزاكورة"
    }
  ],
  "definitions": [],
  "ingestion_status": "ingested"
}