{
  "id": "ma-adala-financial-7396",
  "type": "statute",
  "title": "مرسوم يحدد تعريفة بيع منشورات ومنتجات وخدمات المركز الوطني للتوثيق",
  "status": "in_force",
  "url": "https://adala.justice.gov.ma/resources/829",
  "description": "Discovered from Adala portal, folder: financial (المادة المالية).",
  "provisions": [
    {
      "provision_ref": "art1",
      "section": "1",
      "title": "المادة 1",
      "content": "ى\nتحدد تعريفة بيع منشورات المركز الوطني للتوثيق على النحو التالي:\n الكشافات الراجعية 60............................................درهما؛ الكشافات الجارية (متاعة) العدد 60 ...........................درهما؛ الفهارس الجماعية 60 ............................................درهما؛ المكنز (قائمة المصطلحات المتعددة المواد) 250...........درهما؛ منتجات وثائقية أخرى 50 .......................................در هما.المادة الثانية\nتحدد تعريفة بيع منتجات المركز الوطني للتوثيق على النحو التالي:\n الجذيذات 10,00 ..................................................دراهم للوحدة؛ الجذيذات :استنساخ على ورق للتصوير 1,50…..…….درهم للصفحة؛ نسخ مصورة 1,00 ............................... 29,7 × 21درهم للوحدة؛المادة الثالثة\nتحدد تعريفة خدمات البحث التي ينجزها المركز الوطني للتوثيق على النحو التالي:\n البحث على مطراف (المجذات الوطنية) 50 :درهما لنصف ساعة؛ -البحث على مطراف (المجذات الدولية) 200 :درهم.\n\n -1الجريدة الرسمية عدد 3775بتاريخ 13جمادى اآلخرة 6( 1405مارس ،)1985ص .321\n1"
    },
    {
      "provision_ref": "art4",
      "section": "4",
      "title": "المادة 4",
      "content": "ة\nيحدد ثمن االشتراك السنوي بمجلة متاعة (كشاف جار) ب 200,00درهم ألربعة أعداد."
    },
    {
      "provision_ref": "art5",
      "section": "5",
      "title": "المادة 5",
      "content": "ة\nيمنح تخفيض قدره % 20لإلدارات العامة و % 50للطالب من األثمان المحددة أعاله."
    },
    {
      "provision_ref": "art6",
      "section": "6",
      "title": "المادة 6",
      "content": "ة\nتؤدي اإل دارات والمؤسسات العامة التي يكون لها مطراف للتوثيق البعدي يتيح لها\nاالرتباط بالمجذات العالمية الممكن الوصول إليها انطالقا من المركز الوطني للتوثيق ثمن\nتكلفة األبحاث بالنسبة للمجذات المذكورة ،مضافا إليه % 5لقاء المصاريف العامة و\n30\n\nمن\n\nتكلفة كراء الخط الهاتفي الدولي."
    },
    {
      "provision_ref": "art7",
      "section": "7",
      "title": "المادة 7",
      "content": "ة\nينسخ هذا المرسوم الذي ينشر بالجريدة الرسمية قرار كاتب الدولة لدى الوزير األول\nالمكلف بالتخطيط والتنمية الجهوية رقم 427.76الصادر في 2صفر 9( 1396فبراير\n )1976بتحديد تعريفة بيع منشورات ومنتجات وخدمات المركز الوطني للتوثيق."
    },
    {
      "provision_ref": "art8",
      "section": "8",
      "title": "المادة 8",
      "content": "ة\nيسند تنفيذ ما جاء في هذا المرسوم إلى وزير المالية ووزير التخطيط كل واحد منهما فيما\nيخصه.\nوحرر بالرباط في 7جمادى األولى 29( 1405يناير .)1985\nاإلمضاء :محمد كريم العمراني.\nوقعه بالعطف:\nوزير المالية،\nاإلمضاء :عبد اللطيف الجواهري.\nوزير التخطيط،\nاإلمضاء :عبد الحق التازي.\n\n2"
    }
  ],
  "definitions": [],
  "ingestion_status": "ingested"
}