{
  "id": "ma-adala-financial-8707",
  "type": "statute",
  "title": "مرسوم ملكي يؤذن بموجبه لشركة « فيرست ناسيونال سيتي بنك (المغرب) » في أن تضمن بصفة شخصية وعلى وجه التضامن الملتزمين بإنجاز صفقات الدولة أو البلديات والراسية عليهم عروضها",
  "status": "in_force",
  "url": "https://adala.justice.gov.ma/resources/829",
  "description": "Discovered from Adala portal, folder: financial (المادة المالية).",
  "provisions": [],
  "definitions": [],
  "ingestion_status": "skipped",
  "ingestion_notes": "No extractable article headings found (likely image-only PDF or inaccessible source text)."
}