{
  "id": "ma-adala-financial-8743",
  "type": "statute",
  "title": "مرسوم ملكي بتحديد شروط إصدار سندات لأمد قصير",
  "status": "in_force",
  "url": "https://adala.justice.gov.ma/resources/829",
  "description": "Discovered from Adala portal, folder: financial (المادة المالية).",
  "provisions": [
    {
      "provision_ref": "art1",
      "section": "1",
      "title": "المادة 1",
      "content": "يمكن لوزير المالية بناء على اإلذن في االقتراض المخول بموجب المرسوم الملكي رقم\n 1024.67الصادر في 29رمضان 31( 1387دجنبر )1967بمثابة قانون المالية لسنة ،1968\nأن يصدر سندات ال تتجاوز مدتها سنتين."
    },
    {
      "provision_ref": "art2",
      "section": "2",
      "title": "المادة 2",
      "content": "إ ن االكتتابات في هذه السندات ذات األمد القصير تسجل بحسابات جارية مفتوحة ببنك\nالمغرب في أسماء المقرضين."
    },
    {
      "provision_ref": "art3",
      "section": "3",
      "title": "المادة 3",
      "content": "يصدر وزير المالية قرارا يحدد فيه مدة ومقدار فائدة السندات وجميع كيفيات اإلصدار\nاألخرى."
    },
    {
      "provision_ref": "art4",
      "section": "4",
      "title": "المادة 4",
      "content": "يسند إلى وزير المالية تنفيذ مرسومنا الملكي هذا الذي ينشر بالجريدة الرسمية.\nوحرر بالرباط في 9محرم 8( 1388أبريل .)1968\nاإلمضاء :الحسن بن محمد.\n -1الجريدة الرسمية عدد 2894بتاريخ 18محرم 17( 1388أبريل ،)1968ص .801\n-2-"
    }
  ],
  "definitions": [],
  "ingestion_status": "ingested"
}