{
  "id": "ma-adala-administrative-7104",
  "type": "statute",
  "title": "مرسوم باحداث محافظة على الاملاك العقارية بتارودانت وتحديد دائرة اختصاصها",
  "status": "in_force",
  "url": "https://adala.justice.gov.ma/resources/26",
  "description": "Discovered from Adala portal, folder: administrative (القانون الإداري).",
  "provisions": [
    {
      "provision_ref": "art1",
      "section": "1",
      "title": "المادة 1",
      "content": "ى\nتحدث محافظة على االمالك العقارية بتارودانت يحدد تاريخ افتتاحها بقرار لوزير\nالفالحة واالصالح الزراعي."
    },
    {
      "provision_ref": "art2",
      "section": "2",
      "title": "المادة 2",
      "content": "ة\nتشمل دائرة اختصاص هذه المحافظة جميع اقليم تارودانت."
    },
    {
      "provision_ref": "art3",
      "section": "3",
      "title": "المادة 3",
      "content": "ة\nيسند إلى وزير الفالحة واالصالح الزراعى تنفيذ ما جاء في هذا المرسوم الذي ينشر\nبالجريدة الرسمية.\nوحرر بالرباط في 17من شعبان 5( 1408أبريل )1988\nاالمضاء :الدكتور عز الدين العراقي.\nوقعه بالعطف:\nوزير الفالحة واالصالح الزراعي،\nاالمضاء :عثمان الدمناتي.\n\n - 1الجريدة الرسمية عدد 3936صادرة بتاريخ 18شعبان 6 ( 1408أبريل ،)1988ص .317\n2"
    }
  ],
  "definitions": [],
  "ingestion_status": "ingested"
}