{
  "id": "ma-adala-administrative-7508",
  "type": "statute",
  "title": "مرسوم يحدد بموجبه نظام أجور المدعوين للخدمة المدنية",
  "status": "in_force",
  "url": "https://adala.justice.gov.ma/resources/26",
  "description": "Discovered from Adala portal, folder: administrative (القانون الإداري).",
  "provisions": [
    {
      "provision_ref": "art1",
      "section": "1",
      "title": "المادة 1",
      "content": "- 1تم تغيير الجدول المشار اليه في الفصل األول أعاله ابتداء من فاتح يناير ،1977بمقتضا فصل فريد من\nالمرسوم رقم ،2.77.71الصادر في 12صفر 2( 1397يبراير )1977؛ الجريدة الرسمية عدد 3353الصادرة\nبتاريخ 12صفر 2( 1397يبراير ،)1977ص 373؛\n كما تم تغيير نفس الجدول ابتداء من فاتح مايو ،1979بمقتضا الفصل األول من المرسوم رقم 2.79.315الصادربتاريخ 15من رجب 11( 1399يونيو ،)1979الجريدة الرسمية عدد 3476الصادرة بتاريخ 17رجب 13(1399\nيونيه ،)1979ص 1704؛\n كما تم تغيير نفس الجدول ابتداء من فاتح يناير ،1980بمقتضا الفصل الثاني من المرسوم رقم 2.79.315السالم الذكر؛\n كما تم تغيير نفس الجدول ابتداء من فاتح يناير ،1981بمقتضا الفصل األول من المرسوم رقم 2.81.115الصادر بتاريخ 22من ربيع األول 29( 1401يناير )1981؛ الجريدة الرسمية عدد 3564الصادرة بتاريخ 12\nربيع اآلخر 18( 1401يبراير ،)1981ص 178؛\n كما تم تغيير نفس الجدول ابتداء من فاتح يوليوز 1981؛ بمقتضا الفصل الثاني من المرسوم رقم 2.81.115السالم للذكر؛\n كما تم تغيير نفس الجدول ابتداء من فاتح يوليوز ،1981بمقتضا الفصل األول من المرسوم رقم 2.81.603الصادر بتاريخ 23من شوال 24(1401غشت )1981؛ الجريدة الرسمية عدد 3587الصادرة بتاريخ 29رمضان\n 29( 1401يوليوز ،)1981ص 896؛\n ك ما تم تغيير نفس الجدول بمقتضا الفصل األول من المرسوم رقم 2.82.871؛ الجريدة الرسمية عدد 3661مكرر ،الصادرة بتاريخ 15ربيع األول 31( 1403دجنبر ،)1982ص 1554؛\n كما تم تغيير نفس الجدول بمقتضا المادة األولا من المرسوم رقم ،2.85.199الصادر في فاتح جمادى اآلخرة 22( 1405فبراير )1985؛ الجريدة الرسمية عدد ،3775الصادرة بتاريخ 13جمادى اآلخرة 6( 1405مارس\n ،)1985ص 344؛\nيحدد علا النحو التالي المبلغ التالي المبلغ الشىىىىىىرري ألجرة المدعوين ألداء الخدمة\nالمدنية:\nابتداء من فاتح يوليو :1996\nساللم األجور\n\nالمناطق\n10\nأ\n\n2.504\n\n2.195\n\n2.007\n\nب\n\n2.303\n\n2.021\n\n1.874\n\nج\n\n2.200\n\n1.933\n\n1.805\n\nوزيادة علا ذلك يتقاضا المدعو ألداء الخدمة المدنية إذا كان رب عائلة ،اإلعانة وفق\nالمبلغ المقرر في النصوص الجاري برا العمل.\nابتداء من فاتح يناير :1997\nساللم األجور\n\nالمناطق\n10\nأ\n\n2.562\n\n2.260\n\n2.081\n\nب\n\n2.361\n\n2.086\n\n1.948\n\nج\n\n2.258\n\n1.998\n\n1.879\n\n كما تم تغيير الفصل األول أعاله ،بمقتضا المادة األولا من المرسوم رقم 2.89.467الصادر في 25من محرم 28( 1410أغسطس )1989؛ الجريدة الرسمية عدد 4012الصادرة بتاريخ 18صفر 20( 1410سبتمبر،)1989\nص 1138؛\n ك ما تم تغيير الفصل األول أعاله ،بمقتضا المادة األولا من المرسوم رقم 2.91.42الصادر في 5شعبان 20(1411فبراير )1991؛ الجريدة الرسمية عدد ،4088الصادرة بتاريخ 19شعبان 20(1411فبراير ،)1991\nص 354؛\n كما تم تغيير الجدول المنصوص عليه في الفصل األول أعاله ،بمقتضا المادة األولا من المرسوم رقم 2.94.506الصادر في 26من صفر 5(1415أغسطس )1994؛ الجريدة الرسمية عدد ،4267الصادرة بتاريخ فاتح ربيع\nاألول 10( 1415أغسطس ،)1994ص .1298\n كما تم تغيير ال جدول المنصوص علية في الفصل األول بمقتضا المادة األولا من المرسوم رقم 2.96.816الصادر في 29من جمادى اآلخرة 11( 1417نوفمبر ،)1996الجريدة الرسمية عدد 4436بتاريخ 23رجب\n 5( 1417ديسمبر ،)1996ص .2673\nويتقاضا المدعوون من أرباب العائالت باإلضافة الا ذلك التعويضات العائلية حسب\nالمقادير المعمول برا."
    },
    {
      "provision_ref": "art2",
      "section": "2",
      "title": "المادة 2",
      "content": "يسند الا وزير المالية تنفيذ هذا المرسوم الذي ينشر بالجريدة الرسمية.\nوحرر بالرباط في 14رجب 14( 1393غشت .)1973\nالوزير األول،\nاالمضاء :أحمد عصمان.\nوقعه بالعطم:\nوزير الدولة المكلم بالتعاون وتكوين اإلطارات،\nاالمضاء :الدكتور محمد بنريمة.\n\nوزير المالية،\nاالمضاء :بنسالم جسوس.\n\n5"
    }
  ],
  "definitions": [],
  "ingestion_status": "ingested"
}