{
  "id": "ma-adala-industry-economy-8483",
  "type": "statute",
  "title": "مرسوم تمدد بموجبه الى رهن منتوجات موسم سنة 1964 مقتضيات الظهير الشريف المؤرخ في 22 جمادى الثانية 1361 (7 يوليوز 1942)",
  "status": "in_force",
  "url": "https://adala.justice.gov.ma/resources/31",
  "description": "Discovered from Adala portal, folder: industry-economy (مادة الصناعة والاقتصاد والاستثمار).",
  "provisions": [
    {
      "provision_ref": "art1",
      "section": "1",
      "title": "المادة 1",
      "content": "ان مقتضيات الظهير الشريف المشار اليه أعاله المؤرخ في 22جمادى الثانية 1361\n( 7يوليوز )1942تمدد الى رهن القمح الطرى والقمح الصلب والحبوب الثانوية والمحصوالت\nالزراعية األخرى لموسم سنة .1964"
    },
    {
      "provision_ref": "art2",
      "section": "2",
      "title": "المادة 2",
      "content": "يسند تنفيذ هذا المرسوم الى وزير الفالحة ووكيل الوزارة في المالية كل واحد منهما فيما\nيخصه.\n\n - 1الجريدة الرسمية عدد 2718بتاريخ 27رجب 2( 1384دجنبر ،)1964ص.2462\nوحرر بالرباط في 19رجب 24( 1384نونبر.)1964\nالوزير األول،\nاالمضاء :أحمد أبا حنيني.\nوقع بالعطف:\nوزير الشؤون االقتصادية والمالية،\nاالمضاء :محمد الشرقاوي.\nوزير الفالحة،\nاالمضاء :المحجوبي أحرضان.\n\n3"
    }
  ],
  "definitions": [],
  "ingestion_status": "ingested"
}