{
  "id": "ma-adala-insurance-pension-5122",
  "type": "statute",
  "title": "مرسوم يتعلق بتطبيق المادتين 5-10 و1-248 من القانون رقم 17.99 المتعلق بمدونة التأمينات",
  "status": "in_force",
  "url": "https://adala.justice.gov.ma/resources/59",
  "description": "Discovered from Adala portal, folder: insurance-pension (مادة التأمين و التقاعد).",
  "provisions": [
    {
      "provision_ref": "art1",
      "section": "1",
      "title": "المادة 1",
      "content": "ى\nتطبيقا ألحكام المادتين 10-5و 248-1من القانون المشار إليه أعاله رقم ،17.99تؤهل\nالسلطة الحكومية المكلفة بالمالية ألن تحدد بموجب قرار ،يتخذ باقتراح من هيئة مراقبة\nالتأمينات واالحتياط االجتماعي وبعد الرأي بالمطابقة الصادر عن المجلس العلمي األعلى ،ما\nيلي:\n المقتضيات التطبيقية المتعلقة بعقد التأمين التكافلي وكيفيات عرض عمليات التأمينالتكافلي؛\n معايير تحديد أجرة تسيير حساب التأمين التكافلي ،وكيفيات أدائها لمقاوالت التأمينوإعادة التأمين؛\n\n -1الجريدة الرسمية عدد 6590بتاريخ 3ذو القعدة 27( 1438يوليو ،)2017ص .4267\n كيفيات توزيع الفوائض التقنية والمالية لحسابات التأمين التكافلي على المشتركين فيعمليات التأمين التكافلي."
    },
    {
      "provision_ref": "art2",
      "section": "2",
      "title": "المادة 2",
      "content": "يسند إلى وزير االقتصاد والمالية تنفيذ هذا المرسوم الذي ينشر بالجريدة الرسمية.\nوحرر بالرباط في 25من شوال 20( 1438يوليو .)2017\nاإلمضاء :سعد الدين العثماني.\nوقعه بالعطف:\nوزير االقتصاد والمالية،\nاإلمضاء :محمد بوسعيد.\n\n3"
    }
  ],
  "definitions": [],
  "ingestion_status": "ingested"
}