{
  "id": "ma-adala-administrative-8193",
  "type": "statute",
  "title": "مرسوم يؤذن بموجبه في إصدار سلسلة طوابع بريدية خاصة",
  "status": "in_force",
  "url": "https://adala.justice.gov.ma/resources/26",
  "description": "Discovered from Adala portal, folder: administrative (المادة الإدارية).",
  "provisions": [
    {
      "provision_ref": "art1",
      "section": "1",
      "title": "المادة 1",
      "content": "يؤذن في إصدار سلسلة خاصة لثالثة طوابع بريدية من فئة 0،25و 0،50درهم ودرهم\nواحد تحمل عنوان «لفائدة البندقية -اليونيسكو»."
    },
    {
      "provision_ref": "art2",
      "section": "2",
      "title": "المادة 2",
      "content": "يسند إلى وزير البريد والبرق والتليفون تنفيذ هذا المرسوم الذي ينشر بالجريدة الرسمية.\nوحرر بالرباط في 9شوال 27( 1391نونبر .)1971\nالوزير األول،\nاإلمضاء :محمد كريم العمراني.\nوقعه بالعطف:\nوزير البريد والبرق والتليفون،\nاإلمضاء :الجنرال ادريس بن عمر العلمي.\n\n -1الجريدة الرسمية عدد 3084بتاريخ 20شوال 8( 1391دجنبر ،)1971ص .3098\n-2-"
    }
  ],
  "definitions": [],
  "ingestion_status": "ingested"
}