{
  "id": "ma-adala-tax-5621",
  "type": "statute",
  "title": "مرسوم يوزع بموجبه بين غرف التجارة والصناعة والخدمات وغرف الصناعة التقليدية وغرف الصيد البحري وجامعاتها، الحصة المخصصة لها من عائد الرسم المهني",
  "status": "in_force",
  "url": "https://adala.justice.gov.ma/resources/29",
  "description": "Discovered from Adala portal, folder: tax (المادة الجبائية).",
  "provisions": [
    {
      "provision_ref": "art1",
      "section": "1",
      "title": "المادة 1",
      "content": "ى\nيحدد توزيع عائد الحصة التي تعود لغرف التجارة والصناعة والخدمات وغرف\nالصناعة التقليدية وغرف الصيد البحري واتحاداتها برسم الرسم المهني المحدث بموجب\nالقانون المشار إليه أعاله رقم 47.06على النحو التالي:\n بالنسبة لغرف التجارة والصناعة والخدمات وجمعيتها% 63........................؛ بالنسبة لغرف الصناعة التقليدية وجامعتها% 31......................................؛ بالنسبة لغرف الصيد البحري وجامعتها.% 6...........................................المادة الثانية\nيسند تنفيذ هذا المرسوم الذي ينشر في الجريدة الرسمية إلى وزير االقتصاد والمالية\nووزير الصناعة والتجارة والتكنولوجيات الحديثة ووزير السياحة والصناعة التقليدية ووزير\nالفالحة والصيد البحري كل واحد منهم فيما يخصه.\n -2تم تغيير عنوان المرسوم أعاله ،بمقتضى المادة األولى من المرسوم رقم 2.21.367بتاريخ 15ذي الحجة\n 26( 1442يوليو )2021؛ الجريدة الرسمية عدد 7009بتاريخ 22ذو الحجة 2( 1442أغسطس ،)2021ص\n.5794\n -3تم تغيير مقتضيات المادة األولى أعاله ،بمقتضى المادة األولى من المرسوم رقم 2.21.367بتاريخ 15ذي\nالحجة 26( 1442يوليو )2021؛ الجريدة الرسمية عدد 7009بتاريخ 22ذو الحجة 2( 1442أغسطس ،)2021\nص .5794\n-3-\n\nوحرر بالرباط في 16من ذي الحجة 27( 1428ديسمبر .)2007\nاإلمضاء :عباس الفاسي.\nوقعه بالعطف:\nوزير االقتصاد والمالية،\nاإلمضاء :صالح الدين المزوار.\nوزير الصناعة والتجارة والتكنولوجيات الحديثة،\nاإلمضاء :أحمد رضى شامي.\nوزير السياحة والصناعة التقليدية،\nاإلمضاء :محمد بوسعيد.\nوزير الفالحة والصيد البحري،\nاإلمضاء :عزيز أخنوش.\n\n-4-"
    }
  ],
  "definitions": [],
  "ingestion_status": "ingested"
}