{
  "id": "ma-adala-agriculture-6254",
  "type": "statute",
  "title": "مرسوم بتغيير مبلغ الرسم الجمركي المفروض على استيراد بعض البزور الزيتية",
  "status": "in_force",
  "url": "https://adala.justice.gov.ma/resources/869",
  "description": "Discovered from Adala portal, folder: agriculture (مادة الفلاحة).",
  "provisions": [
    {
      "provision_ref": "art1",
      "section": "1",
      "title": "المادة 1",
      "content": "ى\nتغير وفقا للبيانات الواردة في الملحق بهذا المرسوم تعريفة الرسوم الجمركية الواجب\nاستيفاؤها عند االستيراد المحددة في المادة 1-4من قانون المالية رقم 25.00عن الفترة الممتدة\nمن فاتح يوليو إلى 31ديسمبر .2000\n\n - 1الجريدة الرسمية عدد 5383الصادرة في فاتح ذو الحجة 2( 1426يناير ،)2006ص .5\n2"
    },
    {
      "provision_ref": "art2",
      "section": "2",
      "title": "المادة 2",
      "content": "ة\nيسند إلى وزير المالية والخوصصة تتفيذ هذا المرسوم الذي ينشر في الجريدة الرسمية\nوالذي يعمل بأحكامه ابتداء من 2يناير .2006\nوحرر بالرباط في فاتح ذي الحجة 2( 1426يناير .)2006\nاإلمضاء :إدريس جطو.\nوقعه بالعطف:\nوزير المالية والخوصصة،\nاإلمضاء :فتح هللا ولعلو.\nوزير التجارة الخارجية،\nاإلمضاء :المصطفى مشهوري.\nوزير الفالحة والتنمية القروية\nوالصيد البحري،\nاإلمضاء :محند العنصر.\nالملحق بالمرسوم رقم 2.05.1029الصادر في فاتح ذي الحجة 1426\n( 2يناير )2006بتغيير تعريفة الرسم الجمركي المفروض على استيراد بعض\nالبزور الزيتية\n\n4"
    }
  ],
  "definitions": [],
  "ingestion_status": "ingested"
}